mara/__init__.py
mara/constants.py
mara/status.py
mara/app/__init__.py
mara/app/app.py
mara/app/event_manager.py
mara/app/logging.py
mara/events/__init__.py
mara/events/app.py
mara/events/base.py
mara/events/connection.py
mara/events/server.py
mara/servers/__init__.py
mara/servers/base.py
mara/servers/http.py
mara/servers/socket.py
mara/servers/telnet.py
mara/servers/connections/__init__.py
mara/servers/connections/base.py
mara/servers/connections/http.py
mara/servers/connections/socket.py
mara/servers/connections/telnet.py
mara/storage/__init__.py
mara/storage/base.py
mara/storage/dict.py
mara/timers/__init__.py
mara/timers/base.py
mara/timers/periodic.py
mara-2.1.1.dist-info/LICENSE
mara-2.1.1.dist-info/METADATA
mara-2.1.1.dist-info/WHEEL
mara-2.1.1.dist-info/top_level.txt
mara-2.1.1.dist-info/RECORD
