Metadata-Version: 2.1
Name: mara
Version: 2.1.1
Summary: A framework for network services
Home-page: https://radiac.net/projects/mara/
Author: Richard Terry
Author-email: code@radiac.net
License: BSD
Project-URL: Documentation, https://python-mara.readthedocs.io/
Project-URL: Source, https://github.com/radiac/mara
Project-URL: Tracker, https://github.com/radiac/mara/issues
Keywords: socket telnet http websocket
Platform: UNKNOWN
Classifier: Development Status :: 3 - Alpha
Classifier: Environment :: Web Environment
Classifier: Intended Audience :: Developers
Classifier: License :: OSI Approved :: BSD License
Classifier: Operating System :: OS Independent
Classifier: Topic :: Internet
Classifier: Programming Language :: Python
Classifier: Programming Language :: Python :: 3
Classifier: Programming Language :: Python :: 3 :: Only
Classifier: Programming Language :: Python :: 3.10
Requires-Python: >=3.10
License-File: LICENSE
Requires-Dist: telnetlib3
Requires-Dist: aiohttp
